otto_backend/core/blocks/__init__.py
otto_backend/core/blocks/field.py
otto_backend/core/blocks/metadata.py
otto_backend/core/container_utils/__init__.py
otto_backend/core/container_utils/docker_tools.py
otto_backend/core/data_loaders/image.py
otto_backend/core/implementations/base.py
otto_backend/core/implementations/registry.py
otto_backend/core/input_parser/hf_multimodal_parser.py
otto_backend/core/input_parser/integration_inp_parser.py
otto_backend/core/input_parser/prompt_template.py
otto_backend/core/utils/__init__.py
otto_backend/db/auth.py
otto_backend/db/base.py
otto_backend/db/db_engine.py
otto_backend/db/models/__init__.py
otto_backend/db/models/lambdas.py
otto_backend/db/models/temporary_workflow.py
otto_backend/db/models/tracer.py
otto_backend/db/models/users.py
otto_backend/db/models/workflow_templates.py
otto_m8_backend-0.1.0.dist-info/METADATA
otto_m8_backend-0.1.0.dist-info/WHEEL
otto_m8_backend-0.1.0.dist-info/top_level.txt
otto_m8_backend-0.1.0.dist-info/RECORD
